README.rst
poormanschema.py
setup.py
poormanschema.egg-info/PKG-INFO
poormanschema.egg-info/SOURCES.txt
poormanschema.egg-info/dependency_links.txt
poormanschema.egg-info/requires.txt
poormanschema.egg-info/top_level.txt
poormanschema.egg-info/zip-safe