Metadata-Version: 1.0
Name: poormanschema
Version: 0.0.0.1
Summary: Very simple and effective schema checker
Home-page: UNKNOWN
Author: Benjamin Dauvergne
Author-email: bdauvergne@entrouvert.com
License: MIT
Platform: UNKNOWN
